axosyslog_light/__init__.py
axosyslog_light/common/__init__.py
axosyslog_light/common/asynchronous.py
axosyslog_light/common/blocking.py
axosyslog_light/common/file.py
axosyslog_light/common/network.py
axosyslog_light/common/network_operations.py
axosyslog_light/common/operations.py
axosyslog_light/common/pytest_operations.py
axosyslog_light/common/random_id.py
axosyslog_light/common/session_data.py
axosyslog_light/common/tests/__init__.py
axosyslog_light/common/tests/test_blocking.py
axosyslog_light/driver_io/__init__.py
axosyslog_light/driver_io/clickhouse/clickhouse_io.py
axosyslog_light/driver_io/file/__init__.py
axosyslog_light/driver_io/file/file_io.py
axosyslog_light/driver_io/file/tests/__init__.py
axosyslog_light/driver_io/file/tests/test_file_io.py
axosyslog_light/driver_io/http/__init__.py
axosyslog_light/driver_io/http/http_io.py
axosyslog_light/driver_io/message_readers.py
axosyslog_light/driver_io/network/__init__.py
axosyslog_light/driver_io/network/network_io.py
axosyslog_light/driver_io/opentelemetry/opentelemetry_io.py
axosyslog_light/driver_io/unix_dgram/unix_dgram_io.py
axosyslog_light/executors/__init__.py
axosyslog_light/executors/command_executor.py
axosyslog_light/executors/process_executor.py
axosyslog_light/executors/tests/__init__.py
axosyslog_light/executors/tests/test_command_executor.py
axosyslog_light/executors/tests/test_process_executor.py
axosyslog_light/fixtures.py
axosyslog_light/helpers/__init__.py
axosyslog_light/helpers/clickhouse/clickhouse_server_executor.py
axosyslog_light/helpers/dqtool/__init__.py
axosyslog_light/helpers/dqtool/dqtool.py
axosyslog_light/helpers/dqtool/dqtool_docker_executor.py
axosyslog_light/helpers/dqtool/dqtool_executor.py
axosyslog_light/helpers/dqtool/dqtool_local_executor.py
axosyslog_light/helpers/loggen/__init__.py
axosyslog_light/helpers/loggen/loggen.py
axosyslog_light/helpers/loggen/loggen_docker_executor.py
axosyslog_light/helpers/loggen/loggen_executor.py
axosyslog_light-1.15.0.dist-info/METADATA
axosyslog_light-1.15.0.dist-info/WHEEL
axosyslog_light-1.15.0.dist-info/RECORD
