Metadata-Version: 2.4
Name: axosyslog-light
Version: 1.15.0
Summary: Lightweight End-to-End Test Framework for AxoSyslog.
License: GPL-3.0-or-later
Keywords: axosyslog
Author: Andras Mitzki
Author-email: andras.mitzki@axoflow.com
Requires-Python: >=3.10,<4.0
Classifier: License :: OSI Approved :: GNU General Public License v3 or later (GPLv3+)
Classifier: Programming Language :: Python :: 3
Classifier: Programming Language :: Python :: 3.10
Classifier: Programming Language :: Python :: 3.11
Classifier: Programming Language :: Python :: 3.12
Classifier: Programming Language :: Python :: 3.13
Classifier: Programming Language :: Python :: 3.14
Requires-Dist: clickhouse-connect (>=0.8.18,<0.9.0)
Requires-Dist: filelock (>=3.20.3,<4.0.0)
Requires-Dist: opentelemetry-exporter-otlp-proto-grpc (>=1.31.1,<2.0.0)
Requires-Dist: opentelemetry-sdk (>=1.31.1,<2.0.0)
Requires-Dist: prometheus-client (>=0.21.1,<0.22.0)
Requires-Dist: psutil (>=7.0.0,<8.0.0)
Requires-Dist: pytest (>=8.3.5,<9.0.0)
Requires-Dist: pytest-mock (>=3.14.0,<4.0.0)
Requires-Dist: pytest-xdist (>=3.6.1,<4.0.0)
Requires-Dist: requests (>=2.32.3,<3.0.0)
Requires-Dist: tenacity (>=9.0.0,<10.0.0)
Requires-Dist: virtualenv (>=20.36.1,<21.0.0)
Project-URL: Homepage, https://github.com/axoflow/axosyslog/tests/light
Project-URL: Repository, https://github.com/axoflow/axosyslog/tests/light
